[
  {
    "name": "Alexander Stadium",
    "phone": 441214648008,
    "website": "https://www.birmingham.gov.uk/alexander",
    "image": "AlexanderStadium.jpg",
    "latitude": 52.530936999999994,
    "longitude": -1.9064514900481782,
    "wheelchair": true,
    "events": [
      {
        "Name": "",
        "Date": "",
        "Time": "",
        "Description": ""
      }
    ]
  },
  {
    "name": "Utilita Arena Birmingham",
    "phone": 441217804141,
    "website": "https://www.utilitaarenabham.co.uk",
    "image": "UtilitaArenaBirmingham.jpg",
    "latitude": 52.479717449999995,
    "longitude": -1.915034421788946,
    "wheelchair": true,
    "events": [
      {
        "Name": "",
        "Date": "",
        "Time": "",
        "Description": ""
      }
    ]
  },
  {
    "name": "Lee Valley VeloPark",
    "phone": 443000030613,
    "website": "https://www.better.org.uk/leisure-centre/lee-valley/velopark",
    "image": "LeeValleyVeloPark.jpg",
    "latitude": 51.550376799999995,
    "longitude": -0.015239363509253154,
    "wheelchair": false,
    "events": [
      {
        "Name": "",
        "Date": "",
        "Time": "",
        "Description": ""
      }
    ]
  },
  {
    "name": "Coventry Stadium & Arena",
    "phone": 442476933444,
    "website": "https://www.cbsarena.co.uk",
    "image": "LeeValleyVeloPark.jpg",
    "latitude": 51.550376799999995,
    "longitude": -0.015239363509253154,
    "wheelchair": false,
    "events": [
      {
        "Name": "",
        "Date": "",
        "Time": "",
        "Description": ""
      }
    ]
  }
]